redraw
