Metadata-Version: 2.1
Name: redraw
Version: 0.0.1
Summary: An OpenSource Cloudformation Deployment Framework
Home-page: https://avattathil.github.io/redraw/
Author: Tony Vattathil
Author-email: tonynv@amazon.com
License: Apache License 2.0
Download-URL: https://github.com/avattathil/redraw/tarball/master
Keywords: redraw
Platform: UNKNOWN
Classifier: Development Status :: 2 - Pre-Alpha
Classifier: Intended Audience :: Developers
Classifier: License :: OSI Approved :: Apache Software License
Classifier: Programming Language :: Python :: 3.6
Classifier: Programming Language :: Python :: 3.7
Classifier: Topic :: Software Development :: Libraries
Classifier: Topic :: Software Development :: Testing
Classifier: Operating System :: POSIX :: Linux
Classifier: Operating System :: MacOS :: MacOS X 
